[{"img_id": 115, "imgind": 13, "org_filename": "im_num_115_pattern_4_mod_horizontal_shift_vertical_shift_size_140.png", "pattern": 4, "pattern_name": "hyperbolic", "pattern_noise": 0.8, "intensity_contrast": "medium", "orientation": 2, "orientation_name": "horizontal", "field_of_view": "crop_inside"}, {"img_id": 162, "imgind": 56, "org_filename": "im_num_162_pattern_1_mod_vertical_shift_vertical_shift_size_-70.png", "pattern": 1, "pattern_name": "circular", "pattern_noise": 0.8, "intensity_contrast": "medium", "orientation": 1, "orientation_name": "vertical", "field_of_view": "crop_inside"}, {"img_id": 140, "imgind": 36, "org_filename": "im_num_140_pattern_3_mod_horizontal_shift_vertical_shift_size_-140.png", "pattern": 3, "pattern_name": "spiral", "pattern_noise": 0.8, "intensity_contrast": "medium", "orientation": 2, "orientation_name": "horizontal", "field_of_view": "crop_inside"}, {"img_id": 155, "imgind": 48, "org_filename": "im_num_155_pattern_2_mod_vertical_shift_horizontal_shift_size_70.png", "pattern": 2, "pattern_name": "expansion", "pattern_noise": 0.8, "intensity_contrast": "medium", "orientation": 1, "orientation_name": "vertical", "field_of_view": "crop_inside"}]